pyrhd/__init__.py
pyrhd/downloader/__init__.py
pyrhd/downloader/dler.py
pyrhd/harvester/__init__.py
pyrhd/harvester/hrv8r.py
pyrhd/postproc/__init__.py
pyrhd/postproc/dupy.py
pyrhd/utility/__init__.py
pyrhd/utility/cprint.py
pyrhd/utility/utils.py
pyrhd-0.1.11.dist-info/LICENSE.txt
pyrhd-0.1.11.dist-info/METADATA
pyrhd-0.1.11.dist-info/WHEEL
pyrhd-0.1.11.dist-info/top_level.txt
pyrhd-0.1.11.dist-info/RECORD
